abclf/__init__.py
abclf/__main__.py
abclf/lexicon.pickle
abclf/lexicon_balanced.pickle
abclf/American-British-variety-classifier/ABClf.py
abclf-1.0.1.dist-info/LICENSE
abclf-1.0.1.dist-info/METADATA
abclf-1.0.1.dist-info/WHEEL
abclf-1.0.1.dist-info/entry_points.txt
abclf-1.0.1.dist-info/top_level.txt
abclf-1.0.1.dist-info/RECORD
